MANIFEST.in
README.md
setup.cfg
setup.py
gsyslog/__init__.py
gsyslog/gsyslog.py
gsyslog.egg-info/PKG-INFO
gsyslog.egg-info/SOURCES.txt
gsyslog.egg-info/dependency_links.txt
gsyslog.egg-info/not-zip-safe
gsyslog.egg-info/top_level.txt