Metadata-Version: 1.1
Name: gsyslog
Version: 0.10
Summary: George application logger similar to syslog
Home-page: https://github.com/fulkgl/gsyslog
Author: George L Fulk
Author-email: fulkgl@gmail.com
License: MIT
Keywords: log logger logging gsyslog syslog
Platform: UNKNOWN
Classifier: Development Status :: 3 - Alpha
Classifier: Environment :: Console
Classifier: License :: OSI Approved :: Python Software Foundation License
Classifier: Programming Language :: Python
Classifier: Natural Language :: English
Classifier: Operating System :: OS Independent
Classifier: Topic :: Software Development :: Libraries :: Python Modules
